console_animation/__init__.py
console_animation/decorator.py
tests/__init__.py
tests/test.py
tests/test_decorator.py
console_animation-0.1.3.dist-info/LICENSE
console_animation-0.1.3.dist-info/METADATA
console_animation-0.1.3.dist-info/WHEEL
console_animation-0.1.3.dist-info/top_level.txt
console_animation-0.1.3.dist-info/RECORD
