Metadata-Version: 2.1
Name: console-animation
Version: 0.1.3
Summary: An easy to use decorator to show a console spinner during function execution.
Home-page: https://github.com/KoushikEng/console-animation
Author: Koushik
Author-email: koushikla115@gmail.com
License: UNKNOWN
Platform: UNKNOWN
Classifier: Programming Language :: Python :: 3
Classifier: License :: OSI Approved :: MIT License
Classifier: Operating System :: OS Independent
Requires-Python: >=3.6
